privatetestsetgenerationforllmeval-2.3.1.dist-info/licenses/LICENSE
run/__init__.py
run/agents.py
run/graph.py
run/run.py
run/tools/__init__.py
run/tools/agents.py
run/tools/graph.py
tools/__init__.py
tools/agents.py
tools/graph.py
privatetestsetgenerationforllmeval-2.3.1.dist-info/METADATA
privatetestsetgenerationforllmeval-2.3.1.dist-info/WHEEL
privatetestsetgenerationforllmeval-2.3.1.dist-info/entry_points.txt
privatetestsetgenerationforllmeval-2.3.1.dist-info/top_level.txt
privatetestsetgenerationforllmeval-2.3.1.dist-info/RECORD
