Metadata-Version: 2.4
Name: privatetestsetgenerationforLLMeval
Version: 2.3.1
Summary: A package for generating evaluation set for LLM-based chatbots in a diverse and private manner
Home-page: https://github.com/AmadeusITGroup/privatetestsetgenerationforLLMeval
Author: Ilias
Author-email: ilias.driouich@amadeus.com
Requires-Python: >=3.6
License-File: LICENSE
Requires-Dist: pandas>=1.1.0
Requires-Dist: numpy>=1.19.0
Dynamic: author
Dynamic: author-email
Dynamic: description
Dynamic: description-content-type
Dynamic: home-page
Dynamic: license-file
Dynamic: requires-dist
Dynamic: requires-python
Dynamic: summary
